checkingress/__init__.py
checkingress/_server.py
checkingress/_samples/client.py
checkingress-1.0.3.dist-info/METADATA
checkingress-1.0.3.dist-info/WHEEL
checkingress-1.0.3.dist-info/top_level.txt
checkingress-1.0.3.dist-info/RECORD
