Metadata-Version: 2.1
Name: checkingress
Version: 1.0.3
Summary: Check ingress status of your instance
Home-page: https://devnull.cn
Author: Xizhen Du
Author-email: xizhendu@gmail.com
Requires-Dist: requests
Requires-Dist: theid
